{
    "cookies_policy": {
        "content": {
            "title": "Политики использования файлов cookie",
            "whatIsAcookie": {
                "title": "Что такое печенье?",
                "content": [
                    "Файл cookie — это небольшой объем информации, отправляемый веб-сайтом, и информация о вашем посещении сохраняется в памяти. Обычно это техническая информация, статистическая информация, личные предпочтения и т. д., но не конфиденциальные данные или информация. Файлы cookie не могут повредить ваше устройство и играть важную роль, поскольку без них пользование Интернетом было бы более неприятным."
                ]
            },
            "typeOfCookies": {
                "title": "Типы файлов cookie",
                "content": [
                    "Закон разрешает нам хранить файлы cookie на вашем устройстве, если они строго необходимы для работы нашего сайта (это так называемые технические файлы cookie). Для всех других типов файлов cookie нам нужно ваше разрешение. Помимо технических файлов cookie, на сайте {domain} мы используем аналитические и рекламные файлы cookie. Некоторые файлы cookie размещаются сторонними сервисами, с которыми мы сотрудничаем. Эти типы файлов cookie подробно описаны в Конфигураторе файлов cookie, где вы можете изменить или отозвать свое согласие в любое время. Помимо своей цели, файлы cookie также могут быть следующими:",
                    "В зависимости от того, кому принадлежат эти файлы cookie:",
                    "Собственные файлы cookie: файлы cookie, управляемые и отправленные вам непосредственно компанией ONE SPAIN INSURANCE RISK MANAGEMENTS.",
                    "От третьих лиц: те, которыми управляют и отправляют вам другие сотрудники ONE SPAIN INSURANCE RISK MANAGEMENTS.",
                    "В зависимости от того, как долго хранятся эти файлы cookie:",
                    "Сеансовые файлы cookie: они работают только во время посещения нашего веб-сайта, и как только вы покидаете эту страницу, они перестают работать.",
                    "Постоянные файлы cookie: они работают после того, как вы покинули наш веб-сайт в течение определенного времени, определенного лицом, ответственным за файлы cookie.",
                    "Ниже перечислены все файлы cookie, используемые в ONE SPAIN INSURANCE RISK MANAGEMENT:"
                ]
            },
            "deleteCookies": {
                "title": "Как деактивировать или удалить файлы cookie",
                "content": [
                    "Вы можете отозвать или изменить свое согласие в любое время с помощью Конфигуратора файлов cookie, доступ к которому вы можете получить в любое время по ссылке в этой политике в случае веб-сайта. Но мы также напоминаем вам, что в Интернете вы можете изменить настройки своего браузера в разделе «Параметры» или «Настройки» меню браузера, где вы можете удалить все файлы cookie, которые были приняты ранее. Мы рекомендуем вам использовать функцию «Помощь» вашего браузера, чтобы узнать, как удалить файлы cookie."
                ]
            }
        },
        "tables": {
            "technicalCookies": {
                "title": "ТЕХНИЧЕСКИЕ КУКИ",
                "content": [
                    {
                        "name": "Имя куки",
                        "description": "Описание",
                        "duration": "Продолжительность",
                        "property": "Свойство"
                    },
                    {
                        "name": "ASP.NET_SessionId",
                        "description": "Необходимо для выполнения приложения",
                        "duration": "Сеанс",
                        "property": "Собственное"
                    },
                    {
                        "name": "CJSession",
                        "description": "Присваивает пользователям случайное и зашифрованное значение (ID), позволяющее идентифицировать их как уникальных пользователей без обработки личной идентифицирующей информации",
                        "duration": "1 час",
                        "property": "Собственное"
                    },
                    {
                        "name": "ExpirySession",
                        "description": "Позволяет проверить, остается ли пользователь активным после одного часа",
                        "duration": "30 дней",
                        "property": "Собственное"
                    },
                    {
                        "name": "GASession",
                        "description": "Переносит значение ID куки CJSession в Google Analytics",
                        "duration": "1 час",
                        "property": "Собственное"
                    },
                    {
                        "name": "UserTracker",
                        "description": "Содержит первый ID сеанса пользователя при первом посещении веб-сайта",
                        "duration": "5 лет",
                        "property": "Собственное"
                    },
                    {
                        "name": "UserType",
                        "description": "Позволяет определить, возвращается ли пользователь или посещает веб-сайт впервые",
                        "duration": "1 час",
                        "property": "Собственное"
                    },
                    {
                        "name": "__utmz",
                        "description": "Позволяет получить точку начала навигации пользователя",
                        "duration": "1 час",
                        "property": "Собственное"
                    },
                    {
                        "name": "Cookie_rst",
                        "description": "Позволяет отображать баннер с предупреждением и информацией о куки",
                        "duration": "1 год",
                        "property": "Собственное"
                    },
                    {
                        "name": "Consent",
                        "description": "Позволяет определить, дал ли пользователь согласие на использование куки",
                        "duration": "1 год",
                        "property": "Собственное"
                    },
                    {
                        "name": "IsSessionReset",
                        "description": "Позволяет отслеживать изменения или обновления сеанса пользователя",
                        "duration": "1 день",
                        "property": "Собственное"
                    },
                    {
                        "name": "CarCJSessionId",
                        "description": "Присваивает пользователям случайное и зашифрованное значение (ID) для продукта автострахования, позволяющее идентифицировать их как уникальных пользователей без обработки личной идентифицирующей информации",
                        "duration": "1 час",
                        "property": "Собственное"
                    },
                    {
                        "name": "QPe8d4cca2e2e9",
                        "description": "Позволяет пользователям, которые перешли на страницу с ценами, вернуться на нее, если они нажмут кнопку \"Назад\"",
                        "duration": "1 день",
                        "property": "Собственное"
                    },
                    {
                        "name": "HealthQuotePage",
                        "description": "Позволяет пользователям, которые перешли на страницу с ценами для продукта медицинского страхования, вернуться на нее, если они нажмут кнопку \"Назад\"",
                        "duration": "1 день",
                        "property": "Собственное"
                    },
                    {
                        "name": "captchav3_{Session ID}",
                        "description": "Позволяет проверить, сохранены ли данные Captcha (приложение для идентификации роботов) для ID сеанса",
                        "duration": "2 дня",
                        "property": "Собственное"
                    },
                    {
                        "name": "ip_{cookie ID}",
                        "description": "Позволяет проверить, сохранен ли IP-адрес для ID куки",
                        "duration": "36 часов",
                        "property": "Собственное"
                    },
                    {
                        "name": "Userinformation",
                        "description": "Позволяет сохранять информацию об IP-адресе пользователя на странице продаж",
                        "duration": "Сеанс",
                        "property": "Собственное"
                    },
                    {
                        "name": "Last_Quote",
                        "description": "Позволяет пользователям проверять цены, полученные в последнем сравнении, и пересчитывать их, не отвечая на все вопросы заново",
                        "duration": "5 лет",
                        "property": "Собственное"
                    },
                    {
                        "name": "CJSession",
                        "description": "Присваивает пользователям случайное и зашифрованное значение (ID), позволяющее идентифицировать их как уникальных пользователей без обработки личной идентифицирующей информации",
                        "duration": "1 час",
                        "property": "Собственное"
                    },
                    {
                        "name": "ExpirySession",
                        "description": "Позволяет проверить, остается ли пользователь активным после одного часа",
                        "duration": "30 дней",
                        "property": "Собственное"
                    },
                    {
                        "name": "GASession",
                        "description": "Переносит значение ID куки CJSession в Google Analytics",
                        "duration": "1 час",
                        "property": "Собственное"
                    }
                ]
            },
            "analyticalCookies": {
                "title": "АНАЛИТИЧЕСКИЕ КУКИ",
                "content": [
                    {
                        "name": "Имя куки",
                        "description": "Описание",
                        "duration": "Продолжительность",
                        "property": "Свойство"
                    },
                    {
                        "name": "_ga",
                        "description": "Используется для отслеживания доступности страниц веб-сайта",
                        "duration": "2 года",
                        "property": "Собственное"
                    },
                    {
                        "name": "_glc_au",
                        "description": "Используется Google AdSense для экспериментов с эффективностью рекламы на сайтах, использующих их услуги",
                        "duration": "90 дней",
                        "property": "Собственное"
                    },
                    {
                        "name": "_dc_gtm_UA-7713710-1",
                        "description": "Используется для ограничения процента запросов, которые браузер отправляет на серверы Google",
                        "duration": "1 минута",
                        "property": "Собственное"
                    },
                    {
                        "name": "_gid",
                        "description": "Используется для различения одних пользователей от других без их идентификации",
                        "duration": "24 часа",
                        "property": "Собственное"
                    },
                    {
                        "name": "_gat_UA-7713710-1",
                        "description": "Используется Google AdSense для экспериментов с эффективностью рекламы на сайтах, использующих их услуги",
                        "duration": "1 минута",
                        "property": "Собственное"
                    },
                    {
                        "name": "_gac_UA-7713710-1",
                        "description": "Включает информацию о рекламной кампании, относящейся к пользователю",
                        "duration": "90 дней",
                        "property": "Собственное"
                    },
                    {
                        "name": "vtstep",
                        "description": "Используется для отслеживания пользователей и понимания, сколько из них заканчивается продажами",
                        "duration": "30 дней",
                        "property": "Собственное"
                    },
                    {
                        "name": "datadome",
                        "description": "Используется для обнаружения роботов и атак DDoS",
                        "duration": "1 год",
                        "property": "Собственное"
                    }
                ]
            },
            "thirdCookies": {
                "title": "КУКИ ТРЕТЬИХ СТОРОН",
                "content": [
                    {
                        "name": "Имя куки",
                        "description": "Описание",
                        "duration": "Продолжительность",
                        "property": "Свойство"
                    },
                    {
                        "name": "Conversion, IDE, ANID, DSID, FLC, AID, TAID, exchange_uid",
                        "description": "Используются для показа целевых рекламных объявлений на всем веб-сайте. Вам могут показываться целевые рекламные объявления на основе ваших предыдущих посещений этого веб-сайта",
                        "duration": "1 год",
                        "property": "Третьи лица"
                    },
                    {
                        "name": "AID, DSID, TAID",
                        "description": "Используются для связи вашей активности на разных устройствах. Таким образом, мы согласовываем рекламу, которая появляется на этих устройствах, и измеряем конверсионные события",
                        "duration": "1 год",
                        "property": "Третьи лица"
                    },
                    {
                        "name": "_fbc",
                        "description": "Используется для доставки рекламы, измерения результатов и улучшения их релевантности",
                        "duration": "90 дней",
                        "property": "Третьи лица"
                    },
                    {
                        "name": "_fbp",
                        "description": "Идентифицирует браузеры для предоставления рекламных и аналитических услуг на веб-сайтах",
                        "duration": "90 дней",
                        "property": "Третьи лица"
                    },
                    {
                        "name": "_uetmsclkid",
                        "description": "Используется для точного измерения конверсий путем присвоения уникального идентификатора каждому клику на рекламу и целевой странице",
                        "duration": "90 дней",
                        "property": "Третьи лица"
                    },
                    {
                        "name": "_uetsid",
                        "description": "Используется для улучшения точности конверсий ¿bing? путем присвоения уникального идентификатора каждой сессии",
                        "duration": "30 минут",
                        "property": "Третьи лица"
                    },
                    {
                        "name": "MUID",
                        "description": "Используется для измерения уникальных пользователей Microsoft",
                        "duration": "13 месяцев",
                        "property": "Третьи лица"
                    },
                    {
                        "name": "MUIDB",
                        "description": "Используется для измерения уникальных пользователей Microsoft. Этот файл cookie служит для восстановления уникального идентификатора, управляемого файлом cookie MUID",
                        "duration": "13 месяцев",
                        "property": "Третьи лица"
                    },
                    {
                        "name": "Obuid",
                        "description": "Платформа Native Ads: сохраняет анонимный идентификатор пользователя для регистрации действий, таких как клики, конверсии и т.д.",
                        "duration": "3 месяца",
                        "property": "Третьи лица"
                    },
                    {
                        "name": "t_gid",
                        "description": "Платформа Native Ads: уникальный идентификатор пользователя для назначения атрибуции (клики, конверсии и т.д.)",
                        "duration": "1 год",
                        "property": "Третьи лица"
                    },
                    {
                        "name": "obuid",
                        "description": "Платформа Native Ads: сохраняет анонимный идентификатор пользователя для регистрации действий, таких как клики, конверсии и т.д.",
                        "duration": "3 месяца",
                        "property": "Третьи лица"
                    },
                    {
                        "name": "t_gid",
                        "description": "Платформа Native Ads: уникальный идентификатор пользователя для назначения атрибуции (клики, конверсии и т.д.)",
                        "duration": "1 год",
                        "property": "Третьи лица"
                    },
                    {
                        "name": "Fr",
                        "description": "Это основной рекламный файл cookie Facebook. Используется для предоставления, анализа и повышения релевантности рекламы",
                        "duration": "90 дней",
                        "property": "Третьи лица"
                    },
                    {
                        "name": "oo",
                        "description": "Используется для регистрации решений о прекращении получения рекламы",
                        "duration": "5 лет",
                        "property": "Третьи лица"
                    },
                    {
                        "name": "ddid",
                        "description": "Используется для открытия конкретного местоположения в приложении рекламодателя после его установки",
                        "duration": "28 дней",
                        "property": "Третьи лица"
                    }
                ]
            },
            "advertisingCookies": {
                "title": "КУКИ РЕКЛАМЫ",
                "content": [
                    {
                        "domain": "Домен",
                        "name": "Имя",
                        "description": "Описание",
                        "duration": "Продолжительность",
                        "property": "Свойство"
                    },
                    {
                        "domain": "static.aroa.io",
                        "name": "_adobator",
                        "description": "Эти файлы cookie Adobe позволяют установить связь между поведением пользователя на веб-сайте и устройством, с которого он осуществляет доступ",
                        "duration": "3 месяца",
                        "property": "Третьи лица"
                    },
                    {
                        "domain": "",
                        "name": "_adobator_exp",
                        "description": "Эти файлы cookie Adobe позволяют узнать, присвоен ли пользователю идентификатор Adobe или нет",
                        "duration": "3 месяца",
                        "property": "Третьи лица"
                    },
                    {
                        "domain": "",
                        "name": "_alphonse",
                        "description": "Эти файлы cookie AppNexus позволяют установить связь между поведением пользователя на веб-сайте и устройством, с которого он осуществляет доступ",
                        "duration": "3 месяца",
                        "property": "Третьи лица"
                    },
                    {
                        "domain": "",
                        "name": "_alphonse_exp",
                        "description": "Эти файлы cookie AppNexus позволяют узнать, присвоен ли пользователю идентификатор Adobe или нет",
                        "duration": "3 месяца",
                        "property": "Третьи лица"
                    },
                    {
                        "domain": "",
                        "name": "_darenso",
                        "description": "Эти файлы cookie Datmean позволяют идентифицировать пользователя на веб-сайте и устройстве, с которого он осуществляет доступ",
                        "duration": "3 месяца",
                        "property": "Третьи лица"
                    },
                    {
                        "domain": "",
                        "name": "_deformer_exp",
                        "description": "Этот файл cookie Adform позволяет узнать, присвоен ли пользователю идентификатор Adobe или нет",
                        "duration": "3 месяца",
                        "property": "Третьи лица"
                    },
                    {
                        "domain": "",
                        "name": "_killinchu",
                        "description": "Этот файл cookie Salesforce позволяет установить связь между поведением пользователя на веб-сайте и устройством, с которого он осуществляет доступ",
                        "duration": "3 месяца",
                        "property": "Третьи лица"
                    },
                    {
                        "domain": "",
                        "name": "_killinchu_exp",
                        "description": "Этот файл cookie Salesforce позволяет узнать, присвоен ли пользователю идентификатор Adobe или нет",
                        "duration": "3 месяца",
                        "property": "Третьи лица"
                    },
                    {
                        "domain": "",
                        "name": "_richierich",
                        "description": "Этот файл cookie RichAudience позволяет установить связь между поведением пользователя на веб-сайте и устройством, с которого он осуществляет доступ",
                        "duration": "3 месяца",
                        "property": "Третьи лица"
                    },
                    {
                        "domain": "",
                        "name": "_sesamo",
                        "description": "Эти файлы cookie Datmean позволяют идентифицировать сеанс пользователя на определенном устройстве",
                        "duration": "3 месяца",
                        "property": "Третьи лица"
                    },
                    {
                        "domain": "",
                        "name": "_tortillami",
                        "description": "Этот файл cookie Lotame позволяет установить связь между поведением пользователя на веб-сайте и устройством, с которого он осуществляет доступ",
                        "duration": "3 месяца",
                        "property": "Третьи лица"
                    },
                    {
                        "domain": "",
                        "name": "_tortillami_exp",
                        "description": "Этот файл cookie Lotame позволяет узнать, присвоен ли пользователю идентификатор Adobe или нет",
                        "duration": "3 месяца",
                        "property": "Третьи лица"
                    },
                    {
                        "domain": "",
                        "name": "_trybolera",
                        "description": "Этот файл cookie TTD позволяет установить связь между поведением пользователя на веб-сайте и устройством, с которого он осуществляет доступ",
                        "duration": "3 месяца",
                        "property": "Третьи лица"
                    },
                    {
                        "domain": "",
                        "name": "_wally",
                        "description": "Эти файлы cookie Weborama позволяют установить связь между поведением пользователя на веб-сайте и устройством, с которого он осуществляет доступ",
                        "duration": "3 месяца",
                        "property": "Третьи лица"
                    },
                    {
                        "domain": "",
                        "name": "_wally_exp",
                        "description": "Эти файлы cookie Weborama позволяют узнать, присвоен ли пользователю идентификатор Adobe или нет",
                        "duration": "3 месяца",
                        "property": "Третьи лица"
                    },
                    {
                        "domain": "",
                        "name": "_beyota",
                        "description": "Этот файл cookie Eyeota позволяет установить связь между поведением пользователя на веб-сайте и устройством, с которого он осуществляет доступ",
                        "duration": "3 месяца",
                        "property": "Третьи лица"
                    }
                ]
            }
        }
    }
}