{
  "title": "Potrebbe interessarti",
  "search_options": [
    {
      "title": "Accedi a EvaSeguros.es",
      "description": "Pagamenti, servizi, vantaggi e altro ancora."
    },
    {
      "title": "Assistenza medica",
      "description": "Richiedi assistenza medica virtuale o a domicilio."
    },
    {
      "title": "Copertura assicurativa",
      "description": "Scopri cosa copre la tua assicurazione."
    },
    {
      "title": "Centro assistenza",
      "description": "Approfitta al massimo della tua assicurazione e scopri i tuoi vantaggi."
    }
  ]
}